mmg/__init__.py
mmg/api.py
mmg/base_item.py
mmg/classifier.py
mmg/cli.py
mmg/cli_log.py
mmg/cli_process.py
mmg/config.py
mmg/exceptions.py
mmg/health.py
mmg/output.py
mmg/toc.py
mmg/utils.py
mmg/css/github-dark.css
mmg/css/github-light.css
mmg-2.1.0.dist-info/METADATA
mmg-2.1.0.dist-info/WHEEL
mmg-2.1.0.dist-info/entry_points.txt
mmg-2.1.0.dist-info/licenses/LICENSE
mmg-2.1.0.dist-info/RECORD
