Metadata-Version: 2.4
Name: mmg
Version: 2.1.0
Summary: Command line interface and Python API to generate i18n documents
Project-URL: Homepage, https://mmg.ryul1206.dev/
Project-URL: Repository, https://github.com/ryul1206/multilingual-markdown
Project-URL: Changelog, https://github.com/ryul1206/multilingual-markdown/blob/dev/CHANGELOG.md
Author-email: Hong-ryul Jung <jung.hr.1206@gmail.com>
License-Expression: MIT
License-File: LICENSE
Keywords: cli,i18n,language,markdown,markdown-generator,multilingual
Classifier: License :: OSI Approved :: MIT License
Classifier: Operating System :: MacOS
Classifier: Operating System :: Microsoft :: Windows
Classifier: Operating System :: POSIX :: Linux
Classifier: Programming Language :: Python :: 3.8
Classifier: Programming Language :: Python :: 3.9
Classifier: Programming Language :: Python :: 3.10
Classifier: Programming Language :: Python :: 3.11
Classifier: Programming Language :: Python :: 3.12
Classifier: Programming Language :: Python :: 3.13
Classifier: Topic :: Software Development :: Internationalization
Classifier: Topic :: Software Development :: Localization
Classifier: Topic :: Text Processing :: Markup :: HTML
Classifier: Topic :: Text Processing :: Markup :: Markdown
Requires-Python: <4,>=3.8
Requires-Dist: click>=8.0.0
Requires-Dist: emoji>=0.6.0
Requires-Dist: markdown>=3.3.0
Requires-Dist: nbconvert>=7.6.0
Requires-Dist: pyyaml>=6.0.2
Provides-Extra: pdf
Requires-Dist: weasyprint>=59.0.0; extra == 'pdf'
